{
  "categories": [
    {
      "id": 1,
      "category_name": "Áo khóa"
    },
    {
      "id": 2,
      "category_name": "Công sở"
    },
    {
      "id": 3,
      "category_name": "Thể thao"
    },
    {
      "id": 4,
      "category_name": "Bikini"
    },
    {
      "id": 5,
      "category_name": "Váy"
    },
    {
      "id": 6,
      "category_name": "Quần"
    }
  ],
  "colors": [
    {
      "id": 1,
      "color_name": "Red",
      "color_code": "#FF0000"
    },
    {
      "id": 2,
      "color_name": "Blue",
      "color_code": "#0000FF"
    },
    {
      "id": 3,
      "color_name": "Green",
      "color_code": "#00FF00"
    },
    {
      "id": 4,
      "color_name": "Yellow",
      "color_code": "#FFFF00"
    },
    {
      "id": 5,
      "color_name": "Black",
      "color_code": "#000000"
    },
    {
      "id": 6,
      "color_name": "White",
      "color_code": "#FFFFFF"
    }
  ],
  "products": [
    {
      "id": 1,
      "product_name": "Sơ mi",
      "product_description": "No",
      "colors": [
        1,
        2,
        3
      ],
      "sizes": [
        1,
        2,
        3,
        4,
        5,
        6
      ],
      "img_urls": [
        "https://image/image1.png",
        "https://image/image2.png",
        "https://image/image3.png"
      ],
      "category_id": 5
    },
    {
      "id": 2,
      "product_name": "Váy",
      "product_description": "No comment",
      "colors": [
        1,
        2
      ],
      "sizes": [
        1,
        2,
        3
      ],
      "img_urls": [
        "https://image/image1.png",
        "https://image/image2.png"
      ],
      "category_id": 6
    },
    {
      "id": 5,
      "product_name": "Quần Âu",
      "product_description": "No",
      "colors": [
        1,
        2,
        3
      ],
      "sizes": [
        1,
        2,
        3,
        4,
        5,
        6
      ],
      "img_urls": [
        "https://image/image1.png",
        "https://image/image2.png",
        "https://image/image3.png"
      ],
      "category_id": 6
    },
    {
      "id": 6,
      "product_name": "Bikini",
      "product_description": "No",
      "colors": [
        1,
        2,
        3
      ],
      "sizes": [
        1,
        2,
        3,
        4,
        5,
        6
      ],
      "img_urls": [
        "https://image/image1.png",
        "https://image/image2.png",
        "https://image/image3.png"
      ],
      "category_id": 6
    },
    {
      "id": 7,
      "product_name": "Bamboo",
      "product_description": "No",
      "colors": [
        1,
        2,
        3
      ],
      "sizes": [
        1,
        2,
        3,
        4,
        5,
        6
      ],
      "img_urls": [
        "https://image/image1.png",
        "https://image/image2.png",
        "https://image/image3.png"
      ],
      "category_id": 5
    },
    {
      "id": 8,
      "product_name": "Áo khoác gió",
      "product_description": "No",
      "colors": [
        1,
        2,
        3
      ],
      "sizes": [
        1,
        2,
        3,
        4,
        5,
        6
      ],
      "img_urls": [
        "https://image/image1.png",
        "https://image/image2.png",
        "https://image/image3.png"
      ],
      "category_id": 1
    }
  ],
  "size": [
    {
      "id": 1,
      "name": "S"
    },
    {
      "id": 2,
      "name": "M"
    },
    {
      "id": 3,
      "name": "L"
    },
    {
      "id": 4,
      "name": "XL"
    },
    {
      "id": 5,
      "name": "2XL"
    },
    {
      "id": 6,
      "name": "3Xl"
    }
  ]
}